humanloop/__init__.py
humanloop/agents/__init__.py
humanloop/agents/client.py
humanloop/agents/raw_client.py
humanloop/agents/requests/__init__.py
humanloop/agents/requests/agent_log_request_agent.py
humanloop/agents/requests/agent_log_request_tool_choice.py
humanloop/agents/requests/agent_request_reasoning_effort.py
humanloop/agents/requests/agent_request_stop.py
humanloop/agents/requests/agent_request_template.py
humanloop/agents/requests/agent_request_tools_item.py
humanloop/agents/requests/agents_call_request_agent.py
humanloop/agents/requests/agents_call_request_tool_choice.py
humanloop/agents/requests/agents_call_stream_request_agent.py
humanloop/agents/requests/agents_call_stream_request_tool_choice.py
humanloop/agents/types/__init__.py
humanloop/agents/types/agent_log_request_agent.py
humanloop/agents/types/agent_log_request_tool_choice.py
humanloop/agents/types/agent_request_reasoning_effort.py
humanloop/agents/types/agent_request_stop.py
humanloop/agents/types/agent_request_template.py
humanloop/agents/types/agent_request_tools_item.py
humanloop/agents/types/agents_call_request_agent.py
humanloop/agents/types/agents_call_request_tool_choice.py
humanloop/agents/types/agents_call_stream_request_agent.py
humanloop/agents/types/agents_call_stream_request_tool_choice.py
humanloop/base_client.py
humanloop/client.py
humanloop/context.py
humanloop/core/__init__.py
humanloop/core/api_error.py
humanloop/core/client_wrapper.py
humanloop/core/datetime_utils.py
humanloop/core/file.py
humanloop/core/http_client.py
humanloop/core/http_response.py
humanloop/core/jsonable_encoder.py
humanloop/core/pagination.py
humanloop/core/pydantic_utilities.py
humanloop/core/query_encoder.py
humanloop/core/remove_none_from_dict.py
humanloop/core/request_options.py
humanloop/core/serialization.py
humanloop/core/unchecked_base_model.py
humanloop/datasets/__init__.py
humanloop/datasets/client.py
humanloop/datasets/raw_client.py
humanloop/datasets/types/__init__.py
humanloop-0.8.38.dist-info/METADATA
humanloop-0.8.38.dist-info/WHEEL
humanloop-0.8.38.dist-info/RECORD
