Metadata-Version: 2.1
Name: humanloop
Version: 0.8.38
Summary: 
Requires-Python: >=3.9,<4
Classifier: Intended Audience :: Developers
Classifier: Operating System :: MacOS
Classifier: Operating System :: Microsoft :: Windows
Classifier: Operating System :: OS Independent
Classifier: Operating System :: POSIX
Classifier: Operating System :: POSIX :: Linux
Classifier: Programming Language :: Python
Classifier: Programming Language :: Python :: 3
Classifier: Programming Language :: Python :: 3.9
Classifier: Programming Language :: Python :: 3.10
Classifier: Programming Language :: Python :: 3.11
Classifier: Programming Language :: Python :: 3.12
Classifier: Programming Language :: Python :: 3.8
Classifier: Topic :: Software Development :: Libraries :: Python Modules
Classifier: Typing :: Typed
Requires-Dist: deepdiff (>=8.2.0,<9.0.0)
Requires-Dist: httpx (>=0.21.2)
Requires-Dist: httpx-sse (==0.4.0)
Requires-Dist: mmh3 (>=5.1.0,<6.0.0)
Requires-Dist: opentelemetry-api (>=1.27.0)
Requires-Dist: opentelemetry-instrumentation-anthropic (>=0.20)
Requires-Dist: opentelemetry-instrumentation-bedrock (>=0.15)
Requires-Dist: opentelemetry-instrumentation-cohere (>=0.20)
Requires-Dist: opentelemetry-instrumentation-groq (>=0.29)
Requires-Dist: opentelemetry-instrumentation-openai (>=0.20)
Requires-Dist: opentelemetry-instrumentation-replicate (>=0.20)
Requires-Dist: opentelemetry-proto (>=1.30.0)
Requires-Dist: opentelemetry-sdk (>=1.27.0)
Requires-Dist: parse (>=1)
Requires-Dist: protobuf (>=5.29.3)
Requires-Dist: pydantic (>=1.9.2)
Requires-Dist: pydantic-core (>=2.18.2,<3.0.0)
Requires-Dist: typing_extensions (>=4.0.0)
